{
		"nodes": [
			{
				"Training_Program_Code": "1",
				"Training_Program_Name": "Pre-IMNCI"
			},
			{
				"Training_Program_Code": "2",
				"Training_Program_Name": "General IMNCI"
			},
			{
				"Training_Program_Code": "3",
				"Training_Program_Name": "F-IMNCI"
			},
			{
				"Training_Program_Code": "4",
				"Training_Program_Name": "HBNC"
			},
			{
				"Training_Program_Code": "5",
				"Training_Program_Name": "LBW Protocols"
			},
			{
				"Training_Program_Code": "6",
				"Training_Program_Name": "NBSU"
			},
			{
				"Training_Program_Code": "7",
				"Training_Program_Name": "SAM/MAM"
			},
			{
				"Training_Program_Code": "8",
				"Training_Program_Name": "AMTSL"
			},
			{
				"Training_Program_Code": "9",
				"Training_Program_Name": "SBA"
			},
			{
				"Training_Program_Code": "10",
				"Training_Program_Name": "EMOC"
			},
			{
				"Training_Program_Code": "11",
				"Training_Program_Name": "LSAS"
			},
			{
				"Training_Program_Code": "12",
				"Training_Program_Name": "BEmONC"
			},
			{
				"Training_Program_Code": "13",
				"Training_Program_Name": "IUCD insertion training"
			},
			{
				"Training_Program_Code": "14",
				"Training_Program_Name": "PPIUCD"
			},
			{
				"Training_Program_Code": "15",
				"Training_Program_Name": "NSV"
			},
			{
				"Training_Program_Code": "16",
				"Training_Program_Name": "Contraceptive update"
			},
			{
				"Training_Program_Code": "17",
				"Training_Program_Name": "Mini Lap"
			},
			{
				"Training_Program_Code": "18",
				"Training_Program_Name": "Laparoscopic"
			},
			{
				"Training_Program_Code": "19",
				"Training_Program_Name": "MVA"
			},
			{
				"Training_Program_Code": "20",
				"Training_Program_Name": "RTI/STI"
			},
			{
				"Training_Program_Code": "21",
				"Training_Program_Name": "Blood Storage"
			},
			{
				"Training_Program_Code": "22",
				"Training_Program_Name": "Integrated Refresher Training"
			},
			{
				"Training_Program_Code": "23",
				"Training_Program_Name": "ARSH"
			},
			{
				"Training_Program_Code": "24",
				"Training_Program_Name": "Gender Sensitization"
			},
			{
				"Training_Program_Code": "25",
				"Training_Program_Name": "USG training for Congenital anomaly"
			},
			{
				"Training_Program_Code": "26",
				"Training_Program_Name": "Skill based training for Lab Technician"
			},
			{
				"Training_Program_Code": "27",
				"Training_Program_Name": "Skill based training for Pharmacist"
			},
			{
				"Training_Program_Code": "28",
				"Training_Program_Name": "VHSC members"
			},
			{
				"Training_Program_Code": "29",
				"Training_Program_Name": "Managerial Skills"
			},
			{
				"Training_Program_Code": "30",
				"Training_Program_Name": "Accounts"
			},
			{
				"Training_Program_Code": "31",
				"Training_Program_Name": "Tally"
			},
			{
				"Training_Program_Code": "32",
				"Training_Program_Name": "Bio-Medical Waste Management"
			},
			{
				"Training_Program_Code": "33",
				"Training_Program_Name": "HMIS"
			},
			{
				"Training_Program_Code": "34",
				"Training_Program_Name": "MCTS"
			},
			{
				"Training_Program_Code": "35",
				"Training_Program_Name": "Leadership and motivation"
			},
			{
				"Training_Program_Code": "36",
				"Training_Program_Name": "MCH Skill Lab Training"
			}
		]
	}
